[
  {
    "دسته_بندی": "قیمت ورق ضد سایش",
    "کارخانه_بخش": "قیمت ورق ضد سایش",
    "بروزرسانی": "امروز ( 1404/10/4 )",
    "استاندارد": "ضد ساییش",
    "ضخامت": "8",
    "سایز": "2000*6000",
    "برند": "چینی",
    "حالت": "شیت",
    "محل تحویل": "بنگاه تهران",
    "قیمت (تومان)": "141,360"
  },
  {
    "دسته_بندی": "قیمت ورق ضد سایش",
    "کارخانه_بخش": "قیمت ورق ضد سایش",
    "بروزرسانی": "امروز ( 1404/10/4 )",
    "استاندارد": "ضد ساییش",
    "ضخامت": "10",
    "سایز": "2000*6000",
    "برند": "چینی",
    "حالت": "شیت",
    "محل تحویل": "بنگاه تهران",
    "قیمت (تومان)": "141,360"
  },
  {
    "دسته_بندی": "قیمت ورق ضد سایش",
    "کارخانه_بخش": "قیمت ورق ضد سایش",
    "بروزرسانی": "امروز ( 1404/10/4 )",
    "استاندارد": "ضد ساییش",
    "ضخامت": "12",
    "سایز": "2000*6000",
    "برند": "چینی",
    "حالت": "شیت",
    "محل تحویل": "بنگاه تهران",
    "قیمت (تومان)": "141,360"
  },
  {
    "دسته_بندی": "قیمت ورق ضد سایش",
    "کارخانه_بخش": "قیمت ورق ضد سایش",
    "بروزرسانی": "امروز ( 1404/10/4 )",
    "استاندارد": "ضد ساییش",
    "ضخامت": "15",
    "سایز": "2000*6000",
    "برند": "چینی",
    "حالت": "شیت",
    "محل تحویل": "بنگاه تهران",
    "قیمت (تومان)": "140,910"
  },
  {
    "دسته_بندی": "قیمت ورق ضد سایش",
    "کارخانه_بخش": "قیمت ورق ضد سایش",
    "بروزرسانی": "امروز ( 1404/10/4 )",
    "استاندارد": "ضد ساییش",
    "ضخامت": "25",
    "سایز": "2000*6000",
    "برند": "چینی",
    "حالت": "شیت",
    "محل تحویل": "بنگاه تهران",
    "قیمت (تومان)": "141,360"
  }
]