[
  {
    "دسته_بندی": "قیمت گریتینگ",
    "کارخانه_بخش": "قیمت گریتینگ",
    "بروزرسانی": "امروز ( 1404/10/4 )",
    "نام کالا": "گریتینگ گالوانیزه تسمه * چهارپهلو",
    "حالت": "تسمه*چهارپهلو",
    "تحویل": "کارخانه",
    "قیمت (تومان)": "122,670"
  },
  {
    "دسته_بندی": "قیمت گریتینگ",
    "کارخانه_بخش": "قیمت گریتینگ",
    "بروزرسانی": "امروز ( 1404/10/4 )",
    "نام کالا": "گریتینگ گالوانیزه تسمه * نیم تسمه",
    "حالت": "تسمه*نیم تسمه",
    "تحویل": "کارخانه",
    "قیمت (تومان)": "122,670"
  },
  {
    "دسته_بندی": "قیمت گریتینگ",
    "کارخانه_بخش": "قیمت گریتینگ",
    "بروزرسانی": "امروز ( 1404/10/4 )",
    "نام کالا": "گریتینگ گالوانیزه تسمه * میلگرد",
    "حالت": "تسمه*میلگرد",
    "تحویل": "کارخانه",
    "قیمت (تومان)": "122,670"
  },
  {
    "دسته_بندی": "قیمت گریتینگ",
    "کارخانه_بخش": "قیمت گریتینگ",
    "بروزرسانی": "امروز ( 1404/10/4 )",
    "نام کالا": "گریتینگ گالوانیزه تسمه * تسمه",
    "حالت": "تسمه*تسمه",
    "تحویل": "کارخانه",
    "قیمت (تومان)": "122,670"
  },
  {
    "دسته_بندی": "قیمت گریتینگ",
    "کارخانه_بخش": "قیمت گریتینگ",
    "بروزرسانی": "امروز ( 1404/10/4 )",
    "نام کالا": "گریتینگ فلزی تسمه * چهارپهلو",
    "حالت": "تسمه*چهارپهلو",
    "تحویل": "کارخانه",
    "قیمت (تومان)": "107,270"
  },
  {
    "دسته_بندی": "قیمت گریتینگ",
    "کارخانه_بخش": "قیمت گریتینگ",
    "بروزرسانی": "امروز ( 1404/10/4 )",
    "نام کالا": "گریتینگ فلزی تسمه * نیم تسمه",
    "حالت": "تسمه*نیم تسمه",
    "تحویل": "کارخانه",
    "قیمت (تومان)": "107,270"
  },
  {
    "دسته_بندی": "قیمت گریتینگ",
    "کارخانه_بخش": "قیمت گریتینگ",
    "بروزرسانی": "امروز ( 1404/10/4 )",
    "نام کالا": "گریتینگ فلزی تسمه * میلگرد",
    "حالت": "تسمه*میلگرد",
    "تحویل": "کارخانه",
    "قیمت (تومان)": "107,270"
  },
  {
    "دسته_بندی": "قیمت گریتینگ",
    "کارخانه_بخش": "قیمت گریتینگ",
    "بروزرسانی": "امروز ( 1404/10/4 )",
    "نام کالا": "گریتینگ فلزی تسمه * تسمه",
    "حالت": "تسمه*تسمه",
    "تحویل": "کارخانه",
    "قیمت (تومان)": "107,270"
  },
  {
    "دسته_بندی": "قیمت گریتینگ",
    "کارخانه_بخش": "قیمت گریتینگ",
    "بروزرسانی": "امروز ( 1404/10/4 )",
    "نام کالا": "گریتینگ پله تسمه * نیم تسمه",
    "حالت": "تسمه*نیم تسمه",
    "تحویل": "کارخانه",
    "قیمت (تومان)": "122,760"
  },
  {
    "دسته_بندی": "قیمت گریتینگ",
    "کارخانه_بخش": "قیمت گریتینگ",
    "بروزرسانی": "امروز ( 1404/10/4 )",
    "نام کالا": "گریتینگ پله تسمه * تسمه",
    "حالت": "تسمه*تسمه",
    "تحویل": "کارخانه",
    "قیمت (تومان)": "122,760"
  },
  {
    "دسته_بندی": "قیمت گریتینگ",
    "کارخانه_بخش": "قیمت گریتینگ",
    "بروزرسانی": "امروز ( 1404/10/4 )",
    "نام کالا": "گریتینگ استنلس استیل تسمه * چهارپهلو",
    "حالت": "تسمه*چهارپهلو",
    "تحویل": "کارخانه",
    "قیمت (تومان)": "536,600"
  }
]