{
  "source": "ahanonline.com",
  "urlll": "https://ahanonline.com/product-category/انواع-ورق/ورق-A516/",
  "scraped_attt": "2026-02-25T01:58:03.628Z",
  "headersss": [
    "استاندارد",
    "ضخامت",
    "سایز",
    "برند",
    "حالت",
    "محل تحویل",
    "قیمت (تومان)"
  ],
  "dataaa": [
    {
      "group_infooo": {
        "category_nameee": "بنگاه تهران",
        "update_labelll": "امروز"
      },
      "col_0": "Gr 70",
      "col_1": "5",
      "sizeee": "6000*1500",
      "col_3": "فولاد مبارکه",
      "col_4": "برش خورده",
      "col_5": "بنگاه تهران",
      "price_strrr": "81,230",
      "price_nummm": 81230
    },
    {
      "group_infooo": {
        "category_nameee": "بنگاه تهران",
        "update_labelll": "امروز"
      },
      "col_0": "آخرین بروز رسانی : 1404/12/5 نمودار نوسانات : +0.0%",
      "col_1": "",
      "sizeee": "",
      "col_3": "",
      "col_4": "",
      "col_5": "",
      "price_strrr": "",
      "price_nummm": null
    },
    {
      "group_infooo": {
        "category_nameee": "بنگاه تهران",
        "update_labelll": "امروز"
      },
      "col_0": "Gr 70",
      "col_1": "6",
      "sizeee": "6000*1500",
      "col_3": "فولاد مبارکه",
      "col_4": "برش خورده",
      "col_5": "بنگاه تهران",
      "price_strrr": "72,590",
      "price_nummm": 72590
    },
    {
      "group_infooo": {
        "category_nameee": "بنگاه تهران",
        "update_labelll": "امروز"
      },
      "col_0": "آخرین بروز رسانی : 1404/12/5 نمودار نوسانات : +2.6%",
      "col_1": "",
      "sizeee": "",
      "col_3": "",
      "col_4": "",
      "col_5": "",
      "price_strrr": "",
      "price_nummm": null
    },
    {
      "group_infooo": {
        "category_nameee": "بنگاه تهران",
        "update_labelll": "امروز"
      },
      "col_0": "Gr 70",
      "col_1": "8",
      "sizeee": "6000*1500",
      "col_3": "فولاد مبارکه",
      "col_4": "برش خورده",
      "col_5": "بنگاه تهران",
      "price_strrr": "72,590",
      "price_nummm": 72590
    },
    {
      "group_infooo": {
        "category_nameee": "بنگاه تهران",
        "update_labelll": "امروز"
      },
      "col_0": "آخرین بروز رسانی : 1404/12/5 نمودار نوسانات : +2.6%",
      "col_1": "",
      "sizeee": "",
      "col_3": "",
      "col_4": "",
      "col_5": "",
      "price_strrr": "",
      "price_nummm": null
    },
    {
      "group_infooo": {
        "category_nameee": "بنگاه تهران",
        "update_labelll": "امروز"
      },
      "col_0": "Gr 70",
      "col_1": "10",
      "sizeee": "6000*1500",
      "col_3": "فولاد مبارکه",
      "col_4": "برش خورده",
      "col_5": "بنگاه تهران",
      "price_strrr": "74,370",
      "price_nummm": 74370
    },
    {
      "group_infooo": {
        "category_nameee": "بنگاه تهران",
        "update_labelll": "امروز"
      },
      "col_0": "آخرین بروز رسانی : 1404/12/5 نمودار نوسانات : +3.8%",
      "col_1": "",
      "sizeee": "",
      "col_3": "",
      "col_4": "",
      "col_5": "",
      "price_strrr": "",
      "price_nummm": null
    },
    {
      "group_infooo": {
        "category_nameee": "بنگاه تهران",
        "update_labelll": "امروز"
      },
      "col_0": "Gr 70",
      "col_1": "15",
      "sizeee": "6000*1500",
      "col_3": "فولاد مبارکه",
      "col_4": "برش خورده",
      "col_5": "بنگاه تهران",
      "price_strrr": "74,830",
      "price_nummm": 74830
    },
    {
      "group_infooo": {
        "category_nameee": "بنگاه تهران",
        "update_labelll": "امروز"
      },
      "col_0": "آخرین بروز رسانی : 1404/12/5 نمودار نوسانات : +3.8%",
      "col_1": "",
      "sizeee": "",
      "col_3": "",
      "col_4": "",
      "col_5": "",
      "price_strrr": "",
      "price_nummm": null
    },
    {
      "group_infooo": {
        "category_nameee": "بنگاه تهران",
        "update_labelll": "امروز"
      },
      "col_0": "Gr 70",
      "col_1": "15",
      "sizeee": "1500",
      "col_3": "فولاد مبارکه",
      "col_4": "رول",
      "col_5": "بنگاه تهران",
      "price_strrr": "66,640",
      "price_nummm": 66640
    },
    {
      "group_infooo": {
        "category_nameee": "بنگاه تهران",
        "update_labelll": "امروز"
      },
      "col_0": "آخرین بروز رسانی : 1404/11/27 نمودار نوسانات : +0.8%",
      "col_1": "",
      "sizeee": "",
      "col_3": "",
      "col_4": "",
      "col_5": "",
      "price_strrr": "",
      "price_nummm": null
    }
  ]
}