{
  "source": "ahanonline.com",
  "urlll": "https://ahanonline.com/product-category/انواع-ورق/ورق-شیروانی/",
  "scraped_attt": "2026-05-25T02:28:04.102Z",
  "headersss": [
    "ضخامت",
    "سایز",
    "محل تحویل",
    "واحد",
    "رنگ",
    "قیمت (تومان)"
  ],
  "dataaa": [
    {
      "group_infooo": {
        "category_nameee": "فولاد مبارکه",
        "update_labelll": "امروز"
      },
      "col_0": "0.5",
      "sizeee": "1250",
      "col_2": "بنگاه تهران",
      "unittt": "کیلوگرم",
      "col_4": "قرمز",
      "price_strrr": "200,270",
      "price_nummm": 200270
    },
    {
      "group_infooo": {
        "category_nameee": "فولاد مبارکه",
        "update_labelll": "امروز"
      },
      "col_0": "آخرین بروز رسانی : 1405/3/3 نمودار نوسانات : -1.3%",
      "sizeee": "",
      "col_2": "",
      "unittt": "",
      "col_4": "",
      "price_strrr": "",
      "price_nummm": null
    },
    {
      "group_infooo": {
        "category_nameee": "فولاد مبارکه",
        "update_labelll": "امروز"
      },
      "col_0": "0.5",
      "sizeee": "1250",
      "col_2": "بنگاه تهران",
      "unittt": "کیلوگرم",
      "col_4": "آبی",
      "price_strrr": "200,270",
      "price_nummm": 200270
    },
    {
      "group_infooo": {
        "category_nameee": "فولاد مبارکه",
        "update_labelll": "امروز"
      },
      "col_0": "آخرین بروز رسانی : 1405/3/3 نمودار نوسانات : -1.3%",
      "sizeee": "",
      "col_2": "",
      "unittt": "",
      "col_4": "",
      "price_strrr": "",
      "price_nummm": null
    },
    {
      "group_infooo": {
        "category_nameee": "فولاد مبارکه",
        "update_labelll": "امروز"
      },
      "col_0": "0.5",
      "sizeee": "1250",
      "col_2": "بنگاه تهران",
      "unittt": "کیلوگرم",
      "col_4": "سفید یخچالی",
      "price_strrr": "200,270",
      "price_nummm": 200270
    },
    {
      "group_infooo": {
        "category_nameee": "فولاد مبارکه",
        "update_labelll": "امروز"
      },
      "col_0": "آخرین بروز رسانی : 1405/3/3 نمودار نوسانات : -1.3%",
      "sizeee": "",
      "col_2": "",
      "unittt": "",
      "col_4": "",
      "price_strrr": "",
      "price_nummm": null
    },
    {
      "group_infooo": {
        "category_nameee": "چینی",
        "update_labelll": "امروز"
      },
      "col_0": "0.47",
      "sizeee": "1250",
      "col_2": "بنگاه تهران",
      "unittt": "کیلوگرم",
      "col_4": "قرمز",
      "price_strrr": "191,090",
      "price_nummm": 191090
    },
    {
      "group_infooo": {
        "category_nameee": "چینی",
        "update_labelll": "امروز"
      },
      "col_0": "آخرین بروز رسانی : 1405/3/3 نمودار نوسانات : -4.1%",
      "sizeee": "",
      "col_2": "",
      "unittt": "",
      "col_4": "",
      "price_strrr": "",
      "price_nummm": null
    },
    {
      "group_infooo": {
        "category_nameee": "چینی",
        "update_labelll": "امروز"
      },
      "col_0": "0.47",
      "sizeee": "1250",
      "col_2": "بنگاه تهران",
      "unittt": "کیلوگرم",
      "col_4": "آبی",
      "price_strrr": "191,090",
      "price_nummm": 191090
    },
    {
      "group_infooo": {
        "category_nameee": "چینی",
        "update_labelll": "امروز"
      },
      "col_0": "آخرین بروز رسانی : 1405/3/3 نمودار نوسانات : -4.1%",
      "sizeee": "",
      "col_2": "",
      "unittt": "",
      "col_4": "",
      "price_strrr": "",
      "price_nummm": null
    },
    {
      "group_infooo": {
        "category_nameee": "چینی",
        "update_labelll": "امروز"
      },
      "col_0": "0.47",
      "sizeee": "1250",
      "col_2": "بنگاه تهران",
      "unittt": "کیلوگرم",
      "col_4": "سفید یخچالی",
      "price_strrr": "191,090",
      "price_nummm": 191090
    },
    {
      "group_infooo": {
        "category_nameee": "چینی",
        "update_labelll": "امروز"
      },
      "col_0": "آخرین بروز رسانی : 1405/3/3 نمودار نوسانات : -4.1%",
      "sizeee": "",
      "col_2": "",
      "unittt": "",
      "col_4": "",
      "price_strrr": "",
      "price_nummm": null
    },
    {
      "group_infooo": {
        "category_nameee": "هفت الماس",
        "update_labelll": "امروز"
      },
      "col_0": "0.48",
      "sizeee": "1250",
      "col_2": "بنگاه تهران",
      "unittt": "کیلوگرم",
      "col_4": "قرمز",
      "price_strrr": "190,450",
      "price_nummm": 190450
    },
    {
      "group_infooo": {
        "category_nameee": "هفت الماس",
        "update_labelll": "امروز"
      },
      "col_0": "آخرین بروز رسانی : 1405/3/3 نمودار نوسانات : -1.4%",
      "sizeee": "",
      "col_2": "",
      "unittt": "",
      "col_4": "",
      "price_strrr": "",
      "price_nummm": null
    },
    {
      "group_infooo": {
        "category_nameee": "هفت الماس",
        "update_labelll": "امروز"
      },
      "col_0": "0.48",
      "sizeee": "1250",
      "col_2": "بنگاه تهران",
      "unittt": "کیلوگرم",
      "col_4": "آبی",
      "price_strrr": "190,000",
      "price_nummm": 190000
    },
    {
      "group_infooo": {
        "category_nameee": "هفت الماس",
        "update_labelll": "امروز"
      },
      "col_0": "آخرین بروز رسانی : 1405/3/3 نمودار نوسانات : -1.4%",
      "sizeee": "",
      "col_2": "",
      "unittt": "",
      "col_4": "",
      "price_strrr": "",
      "price_nummm": null
    },
    {
      "group_infooo": {
        "category_nameee": "هفت الماس",
        "update_labelll": "امروز"
      },
      "col_0": "0.48",
      "sizeee": "1250",
      "col_2": "بنگاه تهران",
      "unittt": "کیلوگرم",
      "col_4": "سفید یخچالی",
      "price_strrr": "190,910",
      "price_nummm": 190910
    },
    {
      "group_infooo": {
        "category_nameee": "هفت الماس",
        "update_labelll": "امروز"
      },
      "col_0": "آخرین بروز رسانی : 1405/3/3 نمودار نوسانات : -1.4%",
      "sizeee": "",
      "col_2": "",
      "unittt": "",
      "col_4": "",
      "price_strrr": "",
      "price_nummm": null
    },
    {
      "group_infooo": {
        "category_nameee": "نامشخص",
        "update_labelll": "قیمت انواع ورق شیروانی"
      }
    },
    {
      "group_infooo": {
        "category_nameee": "نامشخص",
        "update_labelll": "قیمت انواع ورق شیروانی"
      }
    },
    {
      "group_infooo": {
        "category_nameee": "نامشخص",
        "update_labelll": "قیمت انواع ورق شیروانی"
      }
    },
    {
      "group_infooo": {
        "category_nameee": "نامشخص",
        "update_labelll": "قیمت انواع ورق شیروانی"
      }
    },
    {
      "group_infooo": {
        "category_nameee": "نامشخص",
        "update_labelll": "قیمت انواع ورق شیروانی"
      }
    },
    {
      "group_infooo": {
        "category_nameee": "نامشخص",
        "update_labelll": "قیمت انواع ورق شیروانی"
      }
    },
    {
      "group_infooo": {
        "category_nameee": "نامشخص",
        "update_labelll": "قیمت انواع ورق شیروانی"
      }
    },
    {
      "group_infooo": {
        "category_nameee": "نامشخص",
        "update_labelll": "قیمت انواع ورق شیروانی"
      }
    }
  ]
}