{
  "source": "ahanonline.com",
  "url": "https://ahanonline.com/product-category/انواع-ورق/ورق-پلی-کربنات/",
  "scraped_at": "2025-12-29T11:52:28.773Z",
  "updated_at": "2025-12-29T11:52:28.771Z",
  "headers": [
    "سایز",
    "ضخامت(mm)",
    "محل انبار",
    "واحد",
    "تاریخ بروزرسانی",
    "قیمت (تومان)",
    "نوسانات",
    "نمودار"
  ],
  "rows": [
    [
      "6*2.10",
      "8",
      "بنگاه تهران",
      "عدد",
      "1404/10/8",
      "7,129,720",
      "0.0%",
      ""
    ],
    [
      "6*2.10",
      "10",
      "بنگاه تهران",
      "عدد",
      "1404/10/8",
      "8,016,700",
      "0.0%",
      ""
    ],
    [
      "6*2.10",
      "6",
      "بنگاه تهران",
      "عدد",
      "1404/10/8",
      "6,195,430",
      "0.0%",
      ""
    ],
    [
      "6*2.10",
      "6",
      "بنگاه تهران",
      "عدد",
      "1404/10/8",
      "4,224,570",
      "0.0%",
      ""
    ],
    [
      "6*2.10",
      "8",
      "بنگاه تهران",
      "عدد",
      "1404/10/8",
      "8,492,060",
      "0.0%",
      ""
    ],
    [
      "6*2.10",
      "6",
      "بنگاه تهران",
      "عدد",
      "1404/10/8",
      "7,334,760",
      "0.0%",
      ""
    ],
    [
      "6*2.10",
      "10",
      "بنگاه تهران",
      "عدد",
      "1404/10/8",
      "9,827,820",
      "0.0%",
      ""
    ],
    [
      "6*2.10",
      "10",
      "بنگاه تهران",
      "عدد",
      "1404/10/8",
      "11,163,750",
      "0.0%",
      ""
    ],
    [
      "6*2.10",
      "8",
      "بنگاه تهران",
      "عدد",
      "1404/10/8",
      "9,916,910",
      "0.0%",
      ""
    ],
    [
      "6*2.10",
      "12",
      "بنگاه تهران",
      "عدد",
      "1404/10/8",
      "16,903,390",
      "0.0%",
      ""
    ],
    [
      "6*2.10",
      "16",
      "بنگاه تهران",
      "عدد",
      "1404/10/8",
      "20,664,800",
      "0.0%",
      ""
    ],
    [
      "6*2.10",
      "14",
      "بنگاه تهران",
      "عدد",
      "1404/10/8",
      "18,677,350",
      "0.0%",
      ""
    ],
    [
      "3.05*2.05",
      "6",
      "بنگاه تهران",
      "عدد",
      "1404/10/8",
      "21,131,710",
      "0.0%",
      ""
    ],
    [
      "3.05*2.05",
      "12",
      "بنگاه تهران",
      "عدد",
      "1404/10/8",
      "4,230,560",
      "0.0%",
      ""
    ],
    [
      "3.05*2.05",
      "2",
      "بنگاه تهران",
      "عدد",
      "1404/10/8",
      "7,065,980",
      "0.0%",
      ""
    ],
    [
      "3.05*2.05",
      "10",
      "بنگاه تهران",
      "عدد",
      "1404/10/8",
      "35,195,910",
      "0.0%",
      ""
    ],
    [
      "3.05*2.05",
      "4",
      "بنگاه تهران",
      "عدد",
      "1404/10/8",
      "14,098,840",
      "0.0%",
      ""
    ],
    [
      "3.05*2.05",
      "8",
      "بنگاه تهران",
      "عدد",
      "1404/10/8",
      "28,163,810",
      "0.0%",
      ""
    ],
    [
      "3.05*2.05",
      "3",
      "بنگاه تهران",
      "عدد",
      "1404/10/8",
      "10,583,180",
      "0.0%",
      ""
    ],
    [
      "6.2*1.25",
      "4",
      "بنگاه تهران",
      "عدد",
      "1404/10/8",
      "3,484,730",
      "0.0%",
      ""
    ],
    [
      "6.2*1.25",
      "8",
      "بنگاه تهران",
      "عدد",
      "1404/10/8",
      "15,819,810",
      "0.0%",
      ""
    ],
    [
      "6.2*1.25",
      "6",
      "بنگاه تهران",
      "عدد",
      "1404/10/8",
      "12,232,730",
      "0.0%",
      ""
    ],
    [
      "6.2*1.25",
      "6",
      "بنگاه تهران",
      "عدد",
      "1404/10/8",
      "9,244,030",
      "0.0%",
      ""
    ],
    [
      "6.2*1.25",
      "4",
      "بنگاه تهران",
      "عدد",
      "1404/10/8",
      "3,353,720",
      "0.0%",
      ""
    ],
    [
      "6.2*1.25",
      "8",
      "بنگاه تهران",
      "عدد",
      "1404/10/8",
      "12,225,970",
      "0.0%",
      ""
    ],
    [
      "جدول ویژگی‌های انواع پلی ‌کربنات",
      "",
      "",
      "",
      "",
      "",
      "",
      ""
    ],
    [
      "نوع پلی کربنات",
      "میزان شفافیت",
      "وزن",
      "میزان مقاومت دربرابر UV",
      "",
      "",
      "",
      ""
    ],
    [
      "پلی کربنات تخت",
      "شفاف‌تر از شیشه است و میزان عبوردهی نور آن %4 از شیشه بیشتر است.",
      "15 کیلو در ضخامت 2 میل و 90 کیلو در ضخامت 12 میل",
      "حداقل 15 سال",
      "",
      "",
      "",
      ""
    ],
    [
      "پلی کربنات دوجداره",
      "شفاف‌تر از شیشه است و میزان عبوردهی نور آن %4 از شیشه بیشتر است.",
      "در ضخامت 4 میل، 7 الی 8 کیلو و در ضخامت 6 میل، از 11 تا 14 کیلو",
      "حداقل 5 و حداکثر 20 سال",
      "",
      "",
      "",
      ""
    ],
    [
      "پلی کربنات لانه زنبوری",
      "شفاف‌تر از شیشه است و میزان عبوردهی نور آن %4 از شیشه بیشتر است.",
      "در ضخامت 6 میل، 16.4 کیلو، ضخامت 8 میل 19 کیلو و ضخامت 10 میل، 22 کیلو",
      "حداقل 15 و حداکثر 25 سال",
      "",
      "",
      "",
      ""
    ],
    [
      "پلی کربنات موجدار",
      "شفاف و حدود 85% در رنگ شیری",
      "ضخامت 4 و 6 و 8 میل",
      "حداقل 15 و حداکثر 20 سال",
      "",
      "",
      "",
      ""
    ],
    [
      "پلی کربنات ذوزنقه ای",
      "شفاف و حدود 85% در رنگ شیری",
      "ضخامت 4 و 6 و 8 میل",
      "حداقل 15 و حداکثر 20 سال",
      "",
      "",
      "",
      ""
    ],
    [
      "مشخصات فنی ورق پلی کربنات",
      "",
      "",
      "",
      "",
      "",
      "",
      ""
    ],
    [
      "ضخامت",
      "از 1 تا 16 میلی‌متر",
      "",
      "",
      "",
      "",
      "",
      ""
    ],
    [
      "ابعاد",
      "600 * 210 و 305 * 205",
      "",
      "",
      "",
      "",
      "",
      ""
    ],
    [
      "مقاومت حرارتی",
      "از 40- تا 120 درجه سانتی‌گراد",
      "",
      "",
      "",
      "",
      "",
      ""
    ],
    [
      "رنگ",
      "آبی، زرد، دودی، شیری، نارنجی، قرمز و خاکستری",
      "",
      "",
      "",
      "",
      "",
      ""
    ],
    [
      "تعداد لایه‌ها",
      "از تک‌جداره تا چندجداره",
      "",
      "",
      "",
      "",
      "",
      ""
    ]
  ],
  "data": [
    {
      "size": "6*2.10",
      "mm": "8",
      "_": "بنگاه تهران",
      "unit": "عدد",
      "date": "1404/10/8",
      "price": "7,129,720",
      "price_numeric": 7129720,
      "col_6": "0.0%",
      "col_7": ""
    },
    {
      "size": "6*2.10",
      "mm": "10",
      "_": "بنگاه تهران",
      "unit": "عدد",
      "date": "1404/10/8",
      "price": "8,016,700",
      "price_numeric": 8016700,
      "col_6": "0.0%",
      "col_7": ""
    },
    {
      "size": "6*2.10",
      "mm": "6",
      "_": "بنگاه تهران",
      "unit": "عدد",
      "date": "1404/10/8",
      "price": "6,195,430",
      "price_numeric": 6195430,
      "col_6": "0.0%",
      "col_7": ""
    },
    {
      "size": "6*2.10",
      "mm": "6",
      "_": "بنگاه تهران",
      "unit": "عدد",
      "date": "1404/10/8",
      "price": "4,224,570",
      "price_numeric": 4224570,
      "col_6": "0.0%",
      "col_7": ""
    },
    {
      "size": "6*2.10",
      "mm": "8",
      "_": "بنگاه تهران",
      "unit": "عدد",
      "date": "1404/10/8",
      "price": "8,492,060",
      "price_numeric": 8492060,
      "col_6": "0.0%",
      "col_7": ""
    },
    {
      "size": "6*2.10",
      "mm": "6",
      "_": "بنگاه تهران",
      "unit": "عدد",
      "date": "1404/10/8",
      "price": "7,334,760",
      "price_numeric": 7334760,
      "col_6": "0.0%",
      "col_7": ""
    },
    {
      "size": "6*2.10",
      "mm": "10",
      "_": "بنگاه تهران",
      "unit": "عدد",
      "date": "1404/10/8",
      "price": "9,827,820",
      "price_numeric": 9827820,
      "col_6": "0.0%",
      "col_7": ""
    },
    {
      "size": "6*2.10",
      "mm": "10",
      "_": "بنگاه تهران",
      "unit": "عدد",
      "date": "1404/10/8",
      "price": "11,163,750",
      "price_numeric": 11163750,
      "col_6": "0.0%",
      "col_7": ""
    },
    {
      "size": "6*2.10",
      "mm": "8",
      "_": "بنگاه تهران",
      "unit": "عدد",
      "date": "1404/10/8",
      "price": "9,916,910",
      "price_numeric": 9916910,
      "col_6": "0.0%",
      "col_7": ""
    },
    {
      "size": "6*2.10",
      "mm": "12",
      "_": "بنگاه تهران",
      "unit": "عدد",
      "date": "1404/10/8",
      "price": "16,903,390",
      "price_numeric": 16903390,
      "col_6": "0.0%",
      "col_7": ""
    },
    {
      "size": "6*2.10",
      "mm": "16",
      "_": "بنگاه تهران",
      "unit": "عدد",
      "date": "1404/10/8",
      "price": "20,664,800",
      "price_numeric": 20664800,
      "col_6": "0.0%",
      "col_7": ""
    },
    {
      "size": "6*2.10",
      "mm": "14",
      "_": "بنگاه تهران",
      "unit": "عدد",
      "date": "1404/10/8",
      "price": "18,677,350",
      "price_numeric": 18677350,
      "col_6": "0.0%",
      "col_7": ""
    },
    {
      "size": "3.05*2.05",
      "mm": "6",
      "_": "بنگاه تهران",
      "unit": "عدد",
      "date": "1404/10/8",
      "price": "21,131,710",
      "price_numeric": 21131710,
      "col_6": "0.0%",
      "col_7": ""
    },
    {
      "size": "3.05*2.05",
      "mm": "12",
      "_": "بنگاه تهران",
      "unit": "عدد",
      "date": "1404/10/8",
      "price": "4,230,560",
      "price_numeric": 4230560,
      "col_6": "0.0%",
      "col_7": ""
    },
    {
      "size": "3.05*2.05",
      "mm": "2",
      "_": "بنگاه تهران",
      "unit": "عدد",
      "date": "1404/10/8",
      "price": "7,065,980",
      "price_numeric": 7065980,
      "col_6": "0.0%",
      "col_7": ""
    },
    {
      "size": "3.05*2.05",
      "mm": "10",
      "_": "بنگاه تهران",
      "unit": "عدد",
      "date": "1404/10/8",
      "price": "35,195,910",
      "price_numeric": 35195910,
      "col_6": "0.0%",
      "col_7": ""
    },
    {
      "size": "3.05*2.05",
      "mm": "4",
      "_": "بنگاه تهران",
      "unit": "عدد",
      "date": "1404/10/8",
      "price": "14,098,840",
      "price_numeric": 14098840,
      "col_6": "0.0%",
      "col_7": ""
    },
    {
      "size": "3.05*2.05",
      "mm": "8",
      "_": "بنگاه تهران",
      "unit": "عدد",
      "date": "1404/10/8",
      "price": "28,163,810",
      "price_numeric": 28163810,
      "col_6": "0.0%",
      "col_7": ""
    },
    {
      "size": "3.05*2.05",
      "mm": "3",
      "_": "بنگاه تهران",
      "unit": "عدد",
      "date": "1404/10/8",
      "price": "10,583,180",
      "price_numeric": 10583180,
      "col_6": "0.0%",
      "col_7": ""
    },
    {
      "size": "6.2*1.25",
      "mm": "4",
      "_": "بنگاه تهران",
      "unit": "عدد",
      "date": "1404/10/8",
      "price": "3,484,730",
      "price_numeric": 3484730,
      "col_6": "0.0%",
      "col_7": ""
    },
    {
      "size": "6.2*1.25",
      "mm": "8",
      "_": "بنگاه تهران",
      "unit": "عدد",
      "date": "1404/10/8",
      "price": "15,819,810",
      "price_numeric": 15819810,
      "col_6": "0.0%",
      "col_7": ""
    },
    {
      "size": "6.2*1.25",
      "mm": "6",
      "_": "بنگاه تهران",
      "unit": "عدد",
      "date": "1404/10/8",
      "price": "12,232,730",
      "price_numeric": 12232730,
      "col_6": "0.0%",
      "col_7": ""
    },
    {
      "size": "6.2*1.25",
      "mm": "6",
      "_": "بنگاه تهران",
      "unit": "عدد",
      "date": "1404/10/8",
      "price": "9,244,030",
      "price_numeric": 9244030,
      "col_6": "0.0%",
      "col_7": ""
    },
    {
      "size": "6.2*1.25",
      "mm": "4",
      "_": "بنگاه تهران",
      "unit": "عدد",
      "date": "1404/10/8",
      "price": "3,353,720",
      "price_numeric": 3353720,
      "col_6": "0.0%",
      "col_7": ""
    },
    {
      "size": "6.2*1.25",
      "mm": "8",
      "_": "بنگاه تهران",
      "unit": "عدد",
      "date": "1404/10/8",
      "price": "12,225,970",
      "price_numeric": 12225970,
      "col_6": "0.0%",
      "col_7": ""
    },
    {
      "size": "جدول ویژگی‌های انواع پلی ‌کربنات",
      "mm": "",
      "_": "",
      "unit": "",
      "date": "",
      "price": "",
      "price_numeric": null,
      "col_6": "",
      "col_7": ""
    },
    {
      "size": "نوع پلی کربنات",
      "mm": "میزان شفافیت",
      "_": "وزن",
      "unit": "میزان مقاومت دربرابر UV",
      "date": "",
      "price": "",
      "price_numeric": null,
      "col_6": "",
      "col_7": ""
    },
    {
      "size": "پلی کربنات تخت",
      "mm": "شفاف‌تر از شیشه است و میزان عبوردهی نور آن %4 از شیشه بیشتر است.",
      "_": "15 کیلو در ضخامت 2 میل و 90 کیلو در ضخامت 12 میل",
      "unit": "حداقل 15 سال",
      "date": "",
      "price": "",
      "price_numeric": null,
      "col_6": "",
      "col_7": ""
    },
    {
      "size": "پلی کربنات دوجداره",
      "mm": "شفاف‌تر از شیشه است و میزان عبوردهی نور آن %4 از شیشه بیشتر است.",
      "_": "در ضخامت 4 میل، 7 الی 8 کیلو و در ضخامت 6 میل، از 11 تا 14 کیلو",
      "unit": "حداقل 5 و حداکثر 20 سال",
      "date": "",
      "price": "",
      "price_numeric": null,
      "col_6": "",
      "col_7": ""
    },
    {
      "size": "پلی کربنات لانه زنبوری",
      "mm": "شفاف‌تر از شیشه است و میزان عبوردهی نور آن %4 از شیشه بیشتر است.",
      "_": "در ضخامت 6 میل، 16.4 کیلو، ضخامت 8 میل 19 کیلو و ضخامت 10 میل، 22 کیلو",
      "unit": "حداقل 15 و حداکثر 25 سال",
      "date": "",
      "price": "",
      "price_numeric": null,
      "col_6": "",
      "col_7": ""
    },
    {
      "size": "پلی کربنات موجدار",
      "mm": "شفاف و حدود 85% در رنگ شیری",
      "_": "ضخامت 4 و 6 و 8 میل",
      "unit": "حداقل 15 و حداکثر 20 سال",
      "date": "",
      "price": "",
      "price_numeric": null,
      "col_6": "",
      "col_7": ""
    },
    {
      "size": "پلی کربنات ذوزنقه ای",
      "mm": "شفاف و حدود 85% در رنگ شیری",
      "_": "ضخامت 4 و 6 و 8 میل",
      "unit": "حداقل 15 و حداکثر 20 سال",
      "date": "",
      "price": "",
      "price_numeric": null,
      "col_6": "",
      "col_7": ""
    },
    {
      "size": "مشخصات فنی ورق پلی کربنات",
      "mm": "",
      "_": "",
      "unit": "",
      "date": "",
      "price": "",
      "price_numeric": null,
      "col_6": "",
      "col_7": ""
    },
    {
      "size": "ضخامت",
      "mm": "از 1 تا 16 میلی‌متر",
      "_": "",
      "unit": "",
      "date": "",
      "price": "",
      "price_numeric": null,
      "col_6": "",
      "col_7": ""
    },
    {
      "size": "ابعاد",
      "mm": "600 * 210 و 305 * 205",
      "_": "",
      "unit": "",
      "date": "",
      "price": "",
      "price_numeric": null,
      "col_6": "",
      "col_7": ""
    },
    {
      "size": "مقاومت حرارتی",
      "mm": "از 40- تا 120 درجه سانتی‌گراد",
      "_": "",
      "unit": "",
      "date": "",
      "price": "",
      "price_numeric": null,
      "col_6": "",
      "col_7": ""
    },
    {
      "size": "رنگ",
      "mm": "آبی، زرد، دودی، شیری، نارنجی، قرمز و خاکستری",
      "_": "",
      "unit": "",
      "date": "",
      "price": "",
      "price_numeric": null,
      "col_6": "",
      "col_7": ""
    },
    {
      "size": "تعداد لایه‌ها",
      "mm": "از تک‌جداره تا چندجداره",
      "_": "",
      "unit": "",
      "date": "",
      "price": "",
      "price_numeric": null,
      "col_6": "",
      "col_7": ""
    }
  ]
}