{
  "source": "ahanonline.com",
  "urlll": "https://ahanonline.com/product-category/انواع-ورق/ورق-A516/",
  "scraped_attt": "2026-02-23T22:57:21.535Z",
  "headersss": [
    "استاندارد",
    "ضخامت",
    "سایز",
    "برند",
    "حالت",
    "محل تحویل",
    "قیمت (تومان)"
  ],
  "dataaa": [
    {
      "group_infooo": {
        "category_nameee": "بنگاه تهران",
        "update_labelll": "امروز"
      },
      "col_0": "Gr 70",
      "col_1": "5",
      "sizeee": "6000*1500",
      "col_3": "فولاد مبارکه",
      "col_4": "برش خورده",
      "col_5": "بنگاه تهران",
      "price_strrr": "81,230",
      "price_nummm": 81230
    },
    {
      "group_infooo": {
        "category_nameee": "بنگاه تهران",
        "update_labelll": "امروز"
      },
      "col_0": "آخرین بروز رسانی : 1404/12/4 نمودار نوسانات : +0.0%",
      "col_1": "",
      "sizeee": "",
      "col_3": "",
      "col_4": "",
      "col_5": "",
      "price_strrr": "",
      "price_nummm": null
    },
    {
      "group_infooo": {
        "category_nameee": "بنگاه تهران",
        "update_labelll": "امروز"
      },
      "col_0": "Gr 70",
      "col_1": "6",
      "sizeee": "6000*1500",
      "col_3": "فولاد مبارکه",
      "col_4": "برش خورده",
      "col_5": "بنگاه تهران",
      "price_strrr": "70,770",
      "price_nummm": 70770
    },
    {
      "group_infooo": {
        "category_nameee": "بنگاه تهران",
        "update_labelll": "امروز"
      },
      "col_0": "آخرین بروز رسانی : 1404/12/4 نمودار نوسانات : +0.0%",
      "col_1": "",
      "sizeee": "",
      "col_3": "",
      "col_4": "",
      "col_5": "",
      "price_strrr": "",
      "price_nummm": null
    },
    {
      "group_infooo": {
        "category_nameee": "بنگاه تهران",
        "update_labelll": "امروز"
      },
      "col_0": "Gr 70",
      "col_1": "8",
      "sizeee": "6000*1500",
      "col_3": "فولاد مبارکه",
      "col_4": "برش خورده",
      "col_5": "بنگاه تهران",
      "price_strrr": "70,770",
      "price_nummm": 70770
    },
    {
      "group_infooo": {
        "category_nameee": "بنگاه تهران",
        "update_labelll": "امروز"
      },
      "col_0": "آخرین بروز رسانی : 1404/12/4 نمودار نوسانات : +0.0%",
      "col_1": "",
      "sizeee": "",
      "col_3": "",
      "col_4": "",
      "col_5": "",
      "price_strrr": "",
      "price_nummm": null
    },
    {
      "group_infooo": {
        "category_nameee": "بنگاه تهران",
        "update_labelll": "امروز"
      },
      "col_0": "Gr 70",
      "col_1": "10",
      "sizeee": "6000*1500",
      "col_3": "فولاد مبارکه",
      "col_4": "برش خورده",
      "col_5": "بنگاه تهران",
      "price_strrr": "71,650",
      "price_nummm": 71650
    },
    {
      "group_infooo": {
        "category_nameee": "بنگاه تهران",
        "update_labelll": "امروز"
      },
      "col_0": "آخرین بروز رسانی : 1404/12/4 نمودار نوسانات : +0.0%",
      "col_1": "",
      "sizeee": "",
      "col_3": "",
      "col_4": "",
      "col_5": "",
      "price_strrr": "",
      "price_nummm": null
    },
    {
      "group_infooo": {
        "category_nameee": "بنگاه تهران",
        "update_labelll": "امروز"
      },
      "col_0": "Gr 70",
      "col_1": "15",
      "sizeee": "6000*1500",
      "col_3": "فولاد مبارکه",
      "col_4": "برش خورده",
      "col_5": "بنگاه تهران",
      "price_strrr": "72,100",
      "price_nummm": 72100
    },
    {
      "group_infooo": {
        "category_nameee": "بنگاه تهران",
        "update_labelll": "امروز"
      },
      "col_0": "آخرین بروز رسانی : 1404/12/4 نمودار نوسانات : +0.0%",
      "col_1": "",
      "sizeee": "",
      "col_3": "",
      "col_4": "",
      "col_5": "",
      "price_strrr": "",
      "price_nummm": null
    },
    {
      "group_infooo": {
        "category_nameee": "بنگاه تهران",
        "update_labelll": "امروز"
      },
      "col_0": "Gr 70",
      "col_1": "15",
      "sizeee": "1500",
      "col_3": "فولاد مبارکه",
      "col_4": "رول",
      "col_5": "بنگاه تهران",
      "price_strrr": "66,640",
      "price_nummm": 66640
    },
    {
      "group_infooo": {
        "category_nameee": "بنگاه تهران",
        "update_labelll": "امروز"
      },
      "col_0": "آخرین بروز رسانی : 1404/11/27 نمودار نوسانات : +0.8%",
      "col_1": "",
      "sizeee": "",
      "col_3": "",
      "col_4": "",
      "col_5": "",
      "price_strrr": "",
      "price_nummm": null
    }
  ]
}